setup.py
IRCLogParser.egg-info/PKG-INFO
IRCLogParser.egg-info/SOURCES.txt
IRCLogParser.egg-info/dependency_links.txt
IRCLogParser.egg-info/requires.txt
IRCLogParser.egg-info/top_level.txt
ext/__init__.py
ext/common_english_words.py
ext/extend_stop_words.py
lib/__init__.py
lib/config.py
lib/nickTracker.py
lib/util.py
lib/validate.py
lib/vis.py
lib/analysis/__init__.py
lib/analysis/channel.py
lib/analysis/community.py
lib/analysis/network.py
lib/analysis/user.py
lib/in_out/__init__.py
lib/in_out/reader.py
lib/in_out/saver.py
test/tests.py