Metadata-Version: 1.1
Name: IRCLogParser
Version: 1.0.6
Summary: A Parser for IRC chat Logs
Home-page: https://github.com/prasadtalasila/IRCLogParser
Author: Prasad Talasila
Author-email: tsrkp@goa.bits-pilani.ac.in
License: MIT
Download-URL: https://github.com/prasadtalasila/IRCLogParser/archive/v1.0.0.tar.gz
Keywords: IRC parser data-analysis research development
Platform: UNKNOWN
